statsforecast/__init__.py
statsforecast/_lib.cpython-312-aarch64-linux-gnu.so
statsforecast/_modidx.py
statsforecast/arima.py
statsforecast/ces.py
statsforecast/core.py
statsforecast/ets.py
statsforecast/feature_engineering.py
statsforecast/garch.py
statsforecast/mfles.py
statsforecast/models.py
statsforecast/mstl.py
statsforecast/tbats.py
statsforecast/theta.py
statsforecast/utils.py
statsforecast/adapters/__init__.py
statsforecast/adapters/prophet.py
statsforecast/distributed/__init__.py
statsforecast/distributed/fugue.py
statsforecast/distributed/multiprocess.py
statsforecast-2.0.2.dist-info/METADATA
statsforecast-2.0.2.dist-info/WHEEL
statsforecast-2.0.2.dist-info/entry_points.txt
statsforecast-2.0.2.dist-info/top_level.txt
statsforecast-2.0.2.dist-info/RECORD
statsforecast-2.0.2.dist-info/licenses/LICENSE
