Metadata-Version: 2.4
Name: statsforecast
Version: 2.0.2
Summary: Time series forecasting suite using statistical models
Home-page: https://github.com/Nixtla/statsforecast/
Author: Nixtla
Author-email: business@nixtla.io
License: Apache Software License 2.0
Keywords: time-series forecasting arima ets
Classifier: Development Status :: 5 - Production/Stable
Classifier: Intended Audience :: Developers
Classifier: Natural Language :: English
Classifier: Programming Language :: Python :: 3.9
Classifier: Programming Language :: Python :: 3.10
Classifier: Programming Language :: Python :: 3.11
Classifier: Programming Language :: Python :: 3.12
Classifier: License :: OSI Approved :: Apache Software License
Requires-Python: >=3.9
License-File: LICENSE
Requires-Dist: cloudpickle
Requires-Dist: coreforecast>=0.0.12
Requires-Dist: numba>=0.55.0
Requires-Dist: numpy>=1.21.6
Requires-Dist: pandas>=1.3.5
Requires-Dist: scipy<1.16.0,>=1.7.3
Requires-Dist: statsmodels>=0.13.2
Requires-Dist: tqdm
Requires-Dist: fugue>=0.8.1
Requires-Dist: utilsforecast>=0.1.4
Requires-Dist: threadpoolctl>=3
Provides-Extra: dev
Requires-Dist: black; extra == "dev"
Requires-Dist: datasetsforecast; extra == "dev"
Requires-Dist: fastcore<=1.7.29; extra == "dev"
Requires-Dist: fire; extra == "dev"
Requires-Dist: nbdev==2.3.25; extra == "dev"
Requires-Dist: nbformat; extra == "dev"
Requires-Dist: nbdev_plotly; extra == "dev"
Requires-Dist: pandas[plot]; extra == "dev"
Requires-Dist: pmdarima; extra == "dev"
Requires-Dist: polars[numpy]; extra == "dev"
Requires-Dist: pre-commit; extra == "dev"
Requires-Dist: prophet; extra == "dev"
Requires-Dist: pyarrow; extra == "dev"
Requires-Dist: pybind11; extra == "dev"
Requires-Dist: pytest; extra == "dev"
Requires-Dist: scikit-learn; extra == "dev"
Requires-Dist: setuptools<70; extra == "dev"
Requires-Dist: supersmoother; extra == "dev"
Requires-Dist: yfinance; extra == "dev"
Provides-Extra: dask
Requires-Dist: dask<=2024.12.1; extra == "dask"
Requires-Dist: fugue[dask]>=0.8.1; extra == "dask"
Provides-Extra: ray
Requires-Dist: fugue[ray]>=0.8.1; python_version < "3.12" and extra == "ray"
Requires-Dist: protobuf<4.0.0,>=3.15.3; python_version < "3.12" and extra == "ray"
Requires-Dist: numpy<2; python_version < "3.12" and extra == "ray"
Requires-Dist: pandas<2.2; python_version < "3.12" and extra == "ray"
Requires-Dist: ray<=2.10; python_version < "3.12" and extra == "ray"
Provides-Extra: spark
Requires-Dist: fugue[spark]>=0.8.1; extra == "spark"
Provides-Extra: plotly
Requires-Dist: plotly; extra == "plotly"
Requires-Dist: plotly-resampler; extra == "plotly"
Provides-Extra: polars
Requires-Dist: polars[numpy]; extra == "polars"
Provides-Extra: all
Requires-Dist: dask<=2024.12.1; extra == "all"
Requires-Dist: fugue[dask]>=0.8.1; extra == "all"
Requires-Dist: fugue[spark]>=0.8.1; extra == "all"
Requires-Dist: plotly; extra == "all"
Requires-Dist: plotly-resampler; extra == "all"
Requires-Dist: polars[numpy]; extra == "all"
Requires-Dist: black; extra == "all"
Requires-Dist: datasetsforecast; extra == "all"
Requires-Dist: fastcore<=1.7.29; extra == "all"
Requires-Dist: fire; extra == "all"
Requires-Dist: nbdev==2.3.25; extra == "all"
Requires-Dist: nbformat; extra == "all"
Requires-Dist: nbdev_plotly; extra == "all"
Requires-Dist: pandas[plot]; extra == "all"
Requires-Dist: pmdarima; extra == "all"
Requires-Dist: polars[numpy]; extra == "all"
Requires-Dist: pre-commit; extra == "all"
Requires-Dist: prophet; extra == "all"
Requires-Dist: pyarrow; extra == "all"
Requires-Dist: pybind11; extra == "all"
Requires-Dist: pytest; extra == "all"
Requires-Dist: scikit-learn; extra == "all"
Requires-Dist: setuptools<70; extra == "all"
Requires-Dist: supersmoother; extra == "all"
Requires-Dist: yfinance; extra == "all"
Requires-Dist: fugue[ray]>=0.8.1; python_version < "3.12" and extra == "all"
Requires-Dist: protobuf<4.0.0,>=3.15.3; python_version < "3.12" and extra == "all"
Requires-Dist: numpy<2; python_version < "3.12" and extra == "all"
Requires-Dist: pandas<2.2; python_version < "3.12" and extra == "all"
Requires-Dist: ray<=2.10; python_version < "3.12" and extra == "all"
Dynamic: author
Dynamic: author-email
Dynamic: classifier
Dynamic: description
Dynamic: description-content-type
Dynamic: home-page
Dynamic: keywords
Dynamic: license
Dynamic: license-file
Dynamic: provides-extra
Dynamic: requires-dist
Dynamic: requires-python
Dynamic: summary
